mediapipe/__init__.py
mediapipe/examples/__init__.py
mediapipe/examples/desktop/__init__.py
mediapipe/examples/desktop/media_sequence/__init__.py
mediapipe/examples/desktop/media_sequence/charades_dataset.py
mediapipe/examples/desktop/media_sequence/demo_dataset.py
mediapipe/examples/desktop/media_sequence/kinetics_dataset.py
mediapipe/examples/desktop/media_sequence/read_demo_dataset.py
mediapipe/examples/desktop/youtube8m/__init__.py
mediapipe/examples/desktop/youtube8m/generate_input_sequence_example.py
mediapipe/examples/desktop/youtube8m/generate_vggish_frozen_graph.py
mediapipe/examples/python/__init__.py
mediapipe/examples/python/upper_body_pose_tracker.py
mediapipe/framework/__init__.py
mediapipe/framework/calculator_options_pb2.py
mediapipe/framework/calculator_pb2.py
mediapipe/framework/calculator_profile_pb2.py
mediapipe/framework/mediapipe_options_pb2.py
mediapipe/framework/packet_factory_pb2.py
mediapipe/framework/packet_generator_pb2.py
mediapipe/framework/status_handler_pb2.py
mediapipe/framework/stream_handler_pb2.py
mediapipe/framework/test_calculators_pb2.py
mediapipe/framework/thread_pool_executor_pb2.py
mediapipe/framework/deps/__init__.py
mediapipe/framework/deps/proto_descriptor_pb2.py
mediapipe/framework/formats/__init__.py
mediapipe/framework/formats/classification_pb2.py
mediapipe/framework/formats/detection_pb2.py
mediapipe/framework/formats/image_file_properties_pb2.py
mediapipe/framework/formats/image_format_pb2.py
mediapipe/framework/formats/landmark_pb2.py
mediapipe/framework/formats/location_data_pb2.py
mediapipe/framework/formats/matrix_data_pb2.py
mediapipe/framework/formats/rect_pb2.py
mediapipe/framework/formats/time_series_header_pb2.py
mediapipe/framework/formats/annotation/__init__.py
mediapipe/framework/formats/annotation/locus_pb2.py
mediapipe/framework/formats/annotation/rasterization_pb2.py
mediapipe/framework/formats/motion/__init__.py
mediapipe/framework/formats/motion/optical_flow_field_data_pb2.py
pikapi-0.0.1.dev1.dist-info/METADATA
pikapi-0.0.1.dev1.dist-info/WHEEL
pikapi-0.0.1.dev1.dist-info/top_level.txt
pikapi-0.0.1.dev1.dist-info/RECORD
