Metadata-Version: 2.1
Name: pikapi
Version: 0.0.1.dev1
Summary: Pikapi is a perception library for interaction with agents.
Home-page: https://github.com/xiong-jie-y/pikapi
Author: xiong jie
Author-email: fwvillage@gmail.com
License: Apache 2.0
Keywords: perception
Platform: UNKNOWN
Requires-Dist: numpy
Requires-Dist: scipy
Requires-Dist: pillow
Requires-Dist: click
Requires-Dist: opencv-python
